{
  "$schema": "component-spec-v1",
  "name": "atom/btn-text",
  "category": "atom",
  "description": "텍스트 버튼 (인라인 액션).",
  "base": {
    "layout": {
      "mode": "NONE"
    },
    "visual": {},
    "children": [
      {
        "kind": "text",
        "id": "--",
        "content": "버튼",
        "exposeAs": "--"
      }
    ]
  },
  "variants": {
    "axes": [
      {
        "name": "property-1",
        "values": [
          "default",
          "variant2"
        ]
      }
    ],
    "overrides": {}
  }
}